{
  "id": "1472328867602628849",
  "name": "other-combinational",
  "code": "OTHERCOMB",
  "category": "🔨 COMBINATIONAL BLOCKS",
  "description": "Devices that perform other combinational functions.",
  "currentCodeId": 6,
  "entries": [
    {
      "id": "1472328901517770888",
      "code": "OTHERCOMB001",
      "path": "OTHERCOMB001_Decrementor"
    },
    {
      "id": "1472328895775899750",
      "code": "OTHERCOMB002",
      "path": "OTHERCOMB002_8-bit_Magnitude_Comparator_w_Equals"
    },
    {
      "id": "1472328890793070656",
      "code": "OTHERCOMB003",
      "path": "OTHERCOMB003_Negator"
    },
    {
      "id": "1472328886720401478",
      "code": "OTHERCOMB004",
      "path": "OTHERCOMB004_Incrementor"
    },
    {
      "id": "1472328855267184881",
      "code": "OTHERCOMB005",
      "path": "OTHERCOMB005_Small_Priority_Circuit"
    },
    {
      "id": "1472328850267574464",
      "code": "OTHERCOMB006",
      "path": "OTHERCOMB006_Fast_Priority_Circuit"
    }
  ]
}